oaktree/__init__.py
oaktree/_oaktree.cpython-310-x86_64-linux-gnu.so
pyoaktree-0.0.3.dist-info/WHEEL
pyoaktree-0.0.3.dist-info/entry_points.txt
pyoaktree-0.0.3.dist-info/METADATA
pyoaktree-0.0.3.dist-info/RECORD
pyoaktree-0.0.3.dist-info/licenses/LICENSE
pyoaktree.libs/libgomp-a34b3233.so.1.0.0
