Metadata-Version: 2.1
Name: pyoaktree
Version: 0.0.3
Summary: Render large point clouds fast using Octrees in Python
Author-Email: Eduardo Arnold <4097245+eduardohenriquearnold@users.noreply.github.com>
Classifier: License :: OSI Approved :: MIT License
Classifier: Topic :: Scientific/Engineering :: Visualization
Classifier: Topic :: Multimedia :: Graphics :: 3D Rendering
Project-URL: Homepage, https://github.com/eduardohenriquearnold/oaktree
Requires-Python: >=3.8
License-File: LICENSE
